neon_phal_plugin_audio_receiver/__init__.py
neon_phal_plugin_audio_receiver/utils.py
neon_phal_plugin_audio_receiver/version.py
neon_phal_plugin_audio_receiver-0.0.4.dist-info/LICENSE.md
neon_phal_plugin_audio_receiver-0.0.4.dist-info/METADATA
neon_phal_plugin_audio_receiver-0.0.4.dist-info/WHEEL
neon_phal_plugin_audio_receiver-0.0.4.dist-info/entry_points.txt
neon_phal_plugin_audio_receiver-0.0.4.dist-info/top_level.txt
neon_phal_plugin_audio_receiver-0.0.4.dist-info/zip-safe
neon_phal_plugin_audio_receiver-0.0.4.dist-info/RECORD
