Metadata-Version: 2.1
Name: neon-phal-plugin-audio-receiver
Version: 0.0.4
Summary: A plugin for OVOS/NEON that allows the user to control the audio receiver options by voice command.
Home-page: https://github.com/NeonGeckoCom/neon-phal-plugin-audio-receiver
Author: mikejgray
Author-email: mike@graywind.org
License: BSD-3
Classifier: Development Status :: 3 - Alpha
Classifier: Intended Audience :: Developers
Classifier: Topic :: Text Processing :: Linguistic
Classifier: License :: OSI Approved :: Apache Software License
Classifier: Programming Language :: Python :: 3.7
Classifier: Programming Language :: Python :: 3.8
Classifier: Programming Language :: Python :: 3.9
Classifier: Programming Language :: Python :: 3.10
Classifier: Programming Language :: Python :: 3.11
License-File: LICENSE.md
Requires-Dist: ovos-plugin-manager
Requires-Dist: ovos-utils
